neverraise/__init__.py
neverraise/py.typed
neverraise/result.py
neverraise-0.1.2.dist-info/METADATA
neverraise-0.1.2.dist-info/WHEEL
neverraise-0.1.2.dist-info/licenses/LICENSE
neverraise-0.1.2.dist-info/RECORD
