Metadata-Version: 2.4
Name: neverraise
Version: 0.1.2
Summary: Result types for python
Author-email: Alexander Ott <66271487+AlexanderHott@users.noreply.github.com>
License: Copyright 2025 Alexander Ott
License-File: LICENSE
Classifier: License :: OSI Approved :: MIT License
Classifier: Operating System :: OS Independent
Classifier: Programming Language :: Python :: 3.13
Requires-Python: >=3.13
